pytestsalt/__init__.py
pytestsalt/_version.py
pytestsalt/fixtures/__init__.py
pytestsalt/fixtures/config.py
pytestsalt/fixtures/daemons.py
pytestsalt/fixtures/dirs.py
pytestsalt/fixtures/log.py
pytestsalt/fixtures/ports.py
pytestsalt/fixtures/stats.py
pytestsalt/salt/__init__.py
pytestsalt/salt/loader.py
pytestsalt/salt/engines/__init__.py
pytestsalt/salt/engines/pytest_engine.py
pytestsalt/salt/log_handlers/__init__.py
pytestsalt/salt/log_handlers/pytest_log_handler.py
pytestsalt/utils/__init__.py
pytestsalt/utils/cli_scripts.py
pytestsalt/utils/compat.py
pytestsalt/utils/log_server_asyncio.py
pytestsalt/utils/log_server_tornado.py
pytest_salt-2020.1.27.dist-info/LICENSE
pytest_salt-2020.1.27.dist-info/METADATA
pytest_salt-2020.1.27.dist-info/WHEEL
pytest_salt-2020.1.27.dist-info/dependency_links.txt
pytest_salt-2020.1.27.dist-info/entry_points.txt
pytest_salt-2020.1.27.dist-info/top_level.txt
pytest_salt-2020.1.27.dist-info/RECORD
