Metadata-Version: 2.1
Name: pytest-salt
Version: 2020.1.27
Summary: Pytest Salt Plugin
Home-page: https://github.com/saltstack/pytest-salt
Author: Pedro Algarvio
Author-email: pedro@algarvio.me
Maintainer: Pedro Algarvio
Maintainer-email: pedro@algarvio.me
License: Apache Software License 2.0
Platform: UNKNOWN
Classifier: Development Status :: 4 - Beta
Classifier: Intended Audience :: Developers
Classifier: Topic :: Software Development :: Testing
Classifier: Programming Language :: Python
Classifier: Programming Language :: Python :: 2
Classifier: Programming Language :: Python :: 2.7
Classifier: Programming Language :: Python :: 3
Classifier: Programming Language :: Python :: 3.5
Classifier: Programming Language :: Python :: 3.6
Classifier: Operating System :: OS Independent
Classifier: License :: OSI Approved :: Apache Software License
Requires-Dist: pytest (>=2.8.1)
Requires-Dist: pytest-tempdir
Requires-Dist: pytest-helpers-namespace
Requires-Dist: psutil (>=4.2.0)
